allenai_common/__init__.py
allenai_common/checks.py
allenai_common/file_utils.py
allenai_common/from_params.py
allenai_common/lazy.py
allenai_common/params.py
allenai_common/registrable.py
allenai_common/tqdm.py
allenai_common-1.1.2.dist-info/LICENSE
allenai_common-1.1.2.dist-info/WHEEL
allenai_common-1.1.2.dist-info/METADATA
allenai_common-1.1.2.dist-info/RECORD
