Metadata-Version: 2.1
Name: allenai-common
Version: 1.1.2
Summary: Params, FromParams, Registrable, Lazy classes from AllenNLP
Home-page: https://github.com/fursovia/allenai-common
License: Apache-2.0
Author: Ivan Fursov
Author-email: fursovia@gmail.com
Requires-Python: >=3.6,<4.0
Classifier: License :: OSI Approved :: Apache Software License
Classifier: Programming Language :: Python :: 3
Classifier: Programming Language :: Python :: 3.6
Classifier: Programming Language :: Python :: 3.7
Classifier: Programming Language :: Python :: 3.8
Classifier: Programming Language :: Python :: 3.9
Requires-Dist: boto3 (>=1.14.0,<2.0.0)
Requires-Dist: filelock (>=3.0.0,<4.0.0)
Requires-Dist: overrides (==3.1.0)
Requires-Dist: requests (>=2.18.0,<3.0.0)
Requires-Dist: tqdm (>=4.19.0,<5.0.0)
Project-URL: Repository, https://github.com/fursovia/allenai-common
